semantic_world/__init__.py
semantic_world/connections.py
semantic_world/degree_of_freedom.py
semantic_world/exceptions.py
semantic_world/geometry.py
semantic_world/graph_of_convex_sets.py
semantic_world/ik_solver.py
semantic_world/prefixed_name.py
semantic_world/raytracer.py
semantic_world/reasoner.py
semantic_world/robots.py
semantic_world/testing.py
semantic_world/types.py
semantic_world/utils.py
semantic_world/variables.py
semantic_world/world.py
semantic_world/world_entity.py
semantic_world/world_state.py
semantic_world/adapters/__init__.py
semantic_world/adapters/mjcf.py
semantic_world/adapters/multi_parser.py
semantic_world/adapters/ros.py
semantic_world/adapters/urdf.py
semantic_world/adapters/usd.py
semantic_world/adapters/viz_marker.py
semantic_world/orm/__init__.py
semantic_world/orm/model.py
semantic_world/orm/ormatic_interface.py
semantic_world/spatial_types/__init__.py
semantic_world/spatial_types/derivatives.py
semantic_world/spatial_types/math.py
semantic_world/spatial_types/spatial_types.py
semantic_world/spatial_types/spatial_types.pyi
semantic_world/spatial_types/symbol_manager.py
semantic_world/views/__init__.py
semantic_world/views/views.py
semantic_world/world_rdr/__init__.py
semantic_world/world_rdr/world_rdr.py
semantic_world/world_rdr/world_views_mcrdr.py
semantic_world/world_rdr/world_views_mcrdr_defs.py
semantic_world/world_rdr/rdr_metadata/world_rdr.json
semantic_world-0.0.3.dist-info/licenses/LICENSE
semantic_world-0.0.3.dist-info/METADATA
semantic_world-0.0.3.dist-info/WHEEL
semantic_world-0.0.3.dist-info/top_level.txt
semantic_world-0.0.3.dist-info/RECORD
