Metadata-Version: 2.4
Name: semantic_world
Version: 0.0.3
Summary: A world model that unifies kinematic information and semantic meaning for robotic world representations.
Author-email: Tom Schierenbeck <tom_sch@uni-bremen.de>
License: LGPL-3.0-only
Project-URL: Source, https://github.com/tomsch420/semantic_world
Project-URL: Bug Tracker, https://github.com/tomsch420/semantic_world/issues
Keywords: robotics
Classifier: Programming Language :: Python :: 3
Classifier: License :: OSI Approved :: GNU General Public License v3 (GPLv3)
Classifier: Operating System :: OS Independent
Requires-Python: >=3.10
License-File: LICENSE
Requires-Dist: rustworkx
Requires-Dist: numpy
Requires-Dist: trimesh
Requires-Dist: typing_extensions
Requires-Dist: urdf-parser-py
Requires-Dist: matplotlib
Requires-Dist: casadi~=3.7.0
Requires-Dist: hypothesis
Requires-Dist: pytest
Requires-Dist: scipy
Requires-Dist: ormatic>=1.1.10
Requires-Dist: sqlacodegen
Requires-Dist: ripple_down_rules>=0.6.51
Requires-Dist: pytest-order
Requires-Dist: sqlalchemy
Requires-Dist: embreex
Requires-Dist: rtree
Requires-Dist: random_events
Requires-Dist: plotly
Requires-Dist: rtree
Requires-Dist: daqp
Requires-Dist: pathlib
Requires-Dist: probabilistic_model
Provides-Extra: gui
Requires-Dist: ripple_down_rules[gui]; extra == "gui"
Dynamic: license-file
